read_overlap-1.0.0.data/scripts/screen_assembly3.py
screen_assembly/__init__.py
screen_assembly/QC/QC.py
screen_assembly/QC/__init__.py
screen_assembly/plot/__init__.py
screen_assembly/plot/plotting.py
screen_assembly/results/__init__.py
screen_assembly/results/results.py
screen_assembly/run/__init__.py
screen_assembly/run/analysis.py
screen_assembly/run/external_programs.py
read_overlap-1.0.0.dist-info/LICENSE
read_overlap-1.0.0.dist-info/METADATA
read_overlap-1.0.0.dist-info/WHEEL
read_overlap-1.0.0.dist-info/top_level.txt
read_overlap-1.0.0.dist-info/RECORD
